README.md
setup.cfg
setup.py
EvalDNN.egg-info/PKG-INFO
EvalDNN.egg-info/SOURCES.txt
EvalDNN.egg-info/dependency_links.txt
EvalDNN.egg-info/requires.txt
EvalDNN.egg-info/top_level.txt
evaldnn/__init__.py
evaldnn/benchmarks/__init__.py
evaldnn/benchmarks/eval_keras.py
evaldnn/benchmarks/eval_mxnet.py
evaldnn/benchmarks/eval_pytorch.py
evaldnn/benchmarks/eval_tensorflow.py
evaldnn/metrics/__init__.py
evaldnn/metrics/accuracy.py
evaldnn/metrics/neuron_coverage.py
evaldnn/metrics/robustness.py
evaldnn/models/__init__.py
evaldnn/models/keras.py
evaldnn/models/mxnet.py
evaldnn/models/pytorch.py
evaldnn/models/tensorflow.py
evaldnn/tests/__init__.py
evaldnn/tests/test_keras.py
evaldnn/tests/test_mxnet.py
evaldnn/tests/test_pytorch.py
evaldnn/tests/test_tensorflow.py
evaldnn/utils/__init__.py
evaldnn/utils/common.py
evaldnn/utils/keras.py
evaldnn/utils/mxnet.py
evaldnn/utils/pytorch.py
evaldnn/utils/tensorflow.py