Metadata-Version: 1.1
Name: EvalDNN
Version: 0.13
Summary: A Platform for Model Evaluation in Deep Learning Systems
Home-page: https://github.com/EvalDNN/EvalDNN
Author: Yongqiang Tian, Zhihua Zeng, Ming Wen, Yepang Liu, Tzu-yang Kuo, Shing-Chi Cheung
Author-email: ytianas@cse.ust.hk
License: MIT
Download-URL: https://github.com/EvalDNN/EvalDNN/archive/0.1.3.tar.gz
Keywords: deep learning,evaluation,accuracy,neuron coverage,robustness,tensorflow,keras,mxnet,pytorch
Platform: UNKNOWN
Classifier: Development Status :: 3 - Alpha
Classifier: Intended Audience :: Developers
Classifier: Topic :: Software Development :: Build Tools
Classifier: License :: OSI Approved :: MIT License
Classifier: Programming Language :: Python :: 3
Classifier: Programming Language :: Python :: 3.4
Classifier: Programming Language :: Python :: 3.5
Classifier: Programming Language :: Python :: 3.6
